aimnet/__init__.py
aimnet/base.py
aimnet/calculators/__init__.py
aimnet/calculators/aimnet2ase.py
aimnet/calculators/aimnet2pysis.py
aimnet/calculators/calculator.py
aimnet/calculators/model_registry.py
aimnet/calculators/model_registry.yaml
aimnet/calculators/nb_kernel_cpu.py
aimnet/calculators/nb_kernel_cuda.py
aimnet/calculators/nbmat.py
aimnet/cli.py
aimnet/config.py
aimnet/constants.py
aimnet/data/__init__.py
aimnet/data/sgdataset.py
aimnet/dftd3_data.pt
aimnet/models/__init__.py
aimnet/models/aimnet2.py
aimnet/models/aimnet2.yaml
aimnet/models/aimnet2_dftd3_wb97m.yaml
aimnet/models/base.py
aimnet/modules/__init__.py
aimnet/modules/aev.py
aimnet/modules/core.py
aimnet/modules/lr.py
aimnet/nbops.py
aimnet/ops.py
aimnet/train/__init__.py
aimnet/train/calc_sae.py
aimnet/train/default_train.yaml
aimnet/train/loss.py
aimnet/train/metrics.py
aimnet/train/pt2jpt.py
aimnet/train/train.py
aimnet/train/utils.py
aimnet-0.0.1.dist-info/LICENSE
aimnet-0.0.1.dist-info/METADATA
aimnet-0.0.1.dist-info/WHEEL
aimnet-0.0.1.dist-info/entry_points.txt
aimnet-0.0.1.dist-info/RECORD
