Metadata-Version: 2.1
Name: aimnet
Version: 0.0.1
Summary: AIMNet Machine Learned Interatomic Potential
Home-page: https://github.com/isayevlab/aimnetcentral
Author: Roman Zubatyuk
Author-email: zubatyuk@gmail.com
Requires-Python: >=3.10,<4.0
Classifier: Programming Language :: Python :: 3
Classifier: Programming Language :: Python :: 3.10
Classifier: Programming Language :: Python :: 3.11
Classifier: Programming Language :: Python :: 3.12
Classifier: Programming Language :: Python :: 3.13
Requires-Dist: click (>=8.1.7,<9.0.0)
Requires-Dist: h5py (>=3.12.1,<4.0.0)
Requires-Dist: ignite (>=1.1.0,<2.0.0)
Requires-Dist: jinja2 (>=3.1.4,<4.0.0)
Requires-Dist: numba (>=0.60.0,<0.61.0)
Requires-Dist: numpy (<2.0)
Requires-Dist: omegaconf (>=2.3.0,<3.0.0)
Requires-Dist: pyyaml (>=6.0.2,<7.0.0)
Requires-Dist: requests (>=2.32.3,<3.0.0)
Requires-Dist: torch (>=2.5.0,<3.0.0)
Requires-Dist: wandb (>=0.18.5,<0.19.0)
Project-URL: Documentation, https://isayevlab.github.io/aimnetcentral/
Project-URL: Repository, https://github.com/isayevlab/aimnetcentral
